simple_salesforce_extends/__init__.py
simple_salesforce_extends/salesforce_extends.py
tests/__init__.py
tests/test_salesforce_client_credential.py
simple_salesforce_extends-0.2.0.dist-info/LICENSE
simple_salesforce_extends-0.2.0.dist-info/METADATA
simple_salesforce_extends-0.2.0.dist-info/WHEEL
simple_salesforce_extends-0.2.0.dist-info/top_level.txt
simple_salesforce_extends-0.2.0.dist-info/RECORD
