Metadata-Version: 2.1
Name: simple-salesforce-extends
Version: 0.2.0
Summary: simple-salesforce extends library
Author-email: shinsaka <shinx1265@gmail.com>
Project-URL: Homepage, https://github.com/shinsaka/simple-salesforce-extends
Classifier: Programming Language :: Python :: 3.11
Classifier: License :: OSI Approved :: MIT License
Requires-Python: >=3.11
License-File: LICENSE
Requires-Dist: simple-salesforce ~=1.12
